icemac.ab.calexport-1.10-py3.7-nspkg.pth
icemac/ab/calexport/__init__.py
icemac/ab/calexport/configure.zcml
icemac/ab/calexport/conftest.py
icemac/ab/calexport/ftesting.zcml
icemac/ab/calexport/interfaces.py
icemac/ab/calexport/permissions.zcml
icemac/ab/calexport/roles.py
icemac/ab/calexport/roles.zcml
icemac/ab/calexport/testing.py
icemac/ab/calexport/browser/__init__.py
icemac/ab/calexport/browser/base.py
icemac/ab/calexport/browser/configure.zcml
icemac/ab/calexport/browser/export.py
icemac/ab/calexport/browser/forecast_event.pt
icemac/ab/calexport/browser/renderer.py
icemac/ab/calexport/browser/tests/__init__.py
icemac/ab/calexport/browser/tests/test_export.py
icemac/ab/calexport/browser/tests/test_renderer.py
icemac/ab/calexport/generations/__init__.py
icemac/ab/calexport/generations/configure.zcml
icemac/ab/calexport/generations/evolve1.py
icemac/ab/calexport/generations/install.py
icemac/ab/calexport/masterdata/__init__.py
icemac/ab/calexport/masterdata/configure.zcml
icemac/ab/calexport/masterdata/export.py
icemac/ab/calexport/masterdata/menu.py
icemac/ab/calexport/masterdata/tests/__init__.py
icemac/ab/calexport/masterdata/tests/test_export.py
icemac/ab/calexport/masterdata/tests/test_menu.py
icemac/ab/calexport/tests/__init__.py
icemac/ab/calexport/tests/test_interfaces.py
icemac/ab/calexport/tests/test_roles.py
icemac.ab.calexport-1.10.dist-info/LICENSE.TXT
icemac.ab.calexport-1.10.dist-info/METADATA
icemac.ab.calexport-1.10.dist-info/WHEEL
icemac.ab.calexport-1.10.dist-info/namespace_packages.txt
icemac.ab.calexport-1.10.dist-info/top_level.txt
icemac.ab.calexport-1.10.dist-info/RECORD
