Metadata-Version: 2.1
Name: icemac.ab.calexport
Version: 1.10
Summary: Calendar export feature for icemac.ab.calendar
Home-page: https://bitbucket.org/icemac/icemac.ab.calexport
Author: Michael Howitz
Author-email: icemac@gmx.net
License: MIT
Download-URL: https://pypi.org/project/icemac.ab.calexport
Keywords: icemac addressbook calendar export html
Platform: UNKNOWN
Classifier: Development Status :: 5 - Production/Stable
Classifier: Environment :: Web Environment
Classifier: Framework :: Zope :: 3
Classifier: License :: OSI Approved :: MIT License
Classifier: Natural Language :: English
Classifier: Natural Language :: German
Classifier: Operating System :: OS Independent
Classifier: Programming Language :: Python :: 2.7
Classifier: Programming Language :: Python :: 2 :: Only
Classifier: Programming Language :: Python :: Implementation :: CPython
Requires-Dist: grokcore.component (>=2.5.1.dev1)
Requires-Dist: icemac.ab.calendar (>=3.2.dev0)
Requires-Dist: icemac.addressbook (>=9.0.dev0)
Requires-Dist: setuptools
Requires-Dist: zope.securitypolicy (>=4.1)
Provides-Extra: test
Requires-Dist: icemac.ab.calendar[test] ; extra == 'test'
